orc_sdk/__init__.py
orc_sdk/constants.py
orc_sdk/docker.py
orc_sdk/env_config.py
orc_sdk/notebook.py
orc_sdk/processor.py
orc_sdk/run_step.py
orc_sdk/step.py
orc_sdk/step_chain.py
orc_sdk/user_info.py
orc_sdk/utils.py
orc_sdk/wizard_client.py
orc_sdk/workflow.py
orc_sdk/workflow_builder/__init__.py
orc_sdk/workflow_builder/base.py
orc_sdk/workflow_builder/local_files.py
orc_sdk/workflow_builder/task_objects.py
orchestracto_sdk-0.0.29.dist-info/METADATA
orchestracto_sdk-0.0.29.dist-info/WHEEL
orchestracto_sdk-0.0.29.dist-info/entry_points.txt
orchestracto_sdk-0.0.29.dist-info/top_level.txt
orchestracto_sdk-0.0.29.dist-info/RECORD
