Metadata-Version: 2.4
Name: orchestracto-sdk
Version: 0.0.29
Author: TractoAI team
Requires-Python: >=3.10
Requires-Dist: cloudpickle~=3.1.1
Requires-Dist: orchestracto-client>=0.8.0
Requires-Dist: PyYAML~=6.0.2
Requires-Dist: requests~=2.32.3
Requires-Dist: typing-extensions~=4.13.0
Requires-Dist: ytsaurus-client~=0.13.28
